MANIFEST.in
README.rst
requirements.txt
setup.cfg
setup.py
esgissue/__init__.py
esgissue/arg_parser.py
esgissue/conf.json
esgissue/config.py
esgissue/constants.py
esgissue/errata_object_factory.py
esgissue/exceptions.py
esgissue/issue_handler.py
esgissue/lextab.py
esgissue/main.py
esgissue/utils.py
esgissue/yacctab.py
esgissue/templates/close.json
esgissue/templates/create.json
esgissue/templates/projects.json
esgissue/templates/retrieve.json
esgissue/templates/update.json
esgissue/tests/__init__.py
esgissue/tests/actionwords.py
esgissue/tests/errata_client_test.py
esgissue/tests/handle_client_test.py
esgissue/tests/pid_ops.py
esgissue/tests/webservice_mockup.py
esgissue_client.egg-info/PKG-INFO
esgissue_client.egg-info/SOURCES.txt
esgissue_client.egg-info/dependency_links.txt
esgissue_client.egg-info/entry_points.txt
esgissue_client.egg-info/not-zip-safe
esgissue_client.egg-info/requires.txt
esgissue_client.egg-info/top_level.txt