Metadata-Version: 1.1
Name: esgissue-client
Version: 2.3.1
Summary: Local client to create, update, close and retrieve ESGF issues
Home-page: https://github.com/ES-DOC/esdoc-errata-client
Author: Atef Ben Nasser
Author-email: abennasser@ipsl.fr
License: UNKNOWN
Platform: Unix
Classifier: Development Status :: 5 - Production/Stable
Classifier: Environment :: Console
Classifier: Intended Audience :: Science/Research
Classifier: Natural Language :: English
Classifier: Operating System :: Unix
Classifier: Programming Language :: Python :: 3
Classifier: Topic :: Scientific/Engineering
Classifier: License :: OSI Approved :: MIT License
